[
  {
    "id": 1,
    "pregunta": "¿Qué animal es más alto ('taller') que un elefante según la canción?",
    "opciones": ["A giraffe", "A cheetah", "A meerkat", "A crocodile"],
    "respuestaCorrecta": 0,
    "explicacion": "La letra de la canción en la lección 3 establece que la jirafa es más alta que el elefante."
  },
  {
    "id": 2,
    "pregunta": "Completa la comparación: 'A cheetah is _____ than a lion'.",
    "opciones": ["colourful", "faster", "larger", "scarier"],
    "respuestaCorrecta": 1,
    "explicacion": "En la estructura de comparativos de la unidad, se asocia al guepardo con la velocidad (faster)."
  },
  {
    "id": 3,
    "pregunta": "¿Cuál es el superlativo de la palabra 'bad'?",
    "opciones": ["the baddest", "the badder", "the worst", "the most bad"],
    "respuestaCorrecta": 2,
    "explicacion": "El recuadro 'Look!' de la lección 6 indica que 'bad' tiene un superlativo irregular: 'the worst'."
  },
  {
    "id": 4,
    "pregunta": "¿Cómo se describe a Baboon al principio de la historia?",
    "opciones": ["He is very kind", "He is very frightened", "He is very small", "He is unfriendly and selfish"],
    "respuestaCorrecta": 3,
    "explicacion": "La historia describe el comportamiento de Baboon como poco amigable y egoísta al no querer compartir el estanque."
  },
  {
    "id": 5,
    "pregunta": "¿Qué animal es 'more colourful' que un flamenco en la canción?",
    "opciones": ["Nothing (A flamingo is more colourful than a...)", "A zebra", "A hyena", "An elephant"],
    "respuestaCorrecta": 0,
    "explicacion": "La canción utiliza al flamenco como el estándar de animal colorido en sus comparaciones."
  },
  {
    "id": 6,
    "pregunta": "¿Qué letra suele seguir al sonido /dʒ/ en palabras como 'giraffe' o 'orange'?",
    "opciones": ["a, o, u", "e, i, y", "b, c, d", "l, m, n"],
    "respuestaCorrecta": 1,
    "explicacion": "La sección de fonética explica que el sonido /dʒ/ aparece antes de las letras e, i, o y."
  },
  {
    "id": 7,
    "pregunta": "Según la historia, ¿por qué Giraffe bebe agua nerviosamente?",
    "opciones": ["Because the water is hot", "Because she is not thirsty", "Because she is frightened of Baboon", "Because she is aggressive"],
    "respuestaCorrecta": 2,
    "explicacion": "El texto de la viñeta 3 dice explícitamente: 'I’m frightened of Baboon, but I’m thirsty!'."
  },
  {
    "id": 8,
    "pregunta": "¿Cuál es el superlativo correcto de 'angry'?",
    "opciones": ["the most angry", "the angrier", "the angryest", "the angriest"],
    "respuestaCorrecta": 3,
    "explicacion": "Siguiendo las reglas de gramática de la lección 6, para adjetivos que terminan en 'y' se cambia por 'i' y se añade '-est'."
  },
  {
    "id": 9,
    "pregunta": "En la sección de repaso, ¿qué animales se mencionan como en peligro de extinción ('endangered')?",
    "opciones": ["Koalas and elephants", "Zebas and giraffes", "Lions and tigers", "Crocodiles and hyenas"],
    "respuestaCorrecta": 0,
    "explicacion": "La lección 8 menciona específicamente que los koalas y elefantes están en peligro de extinción."
  },
  {
    "id": 10,
    "pregunta": "¿Qué sonido tiene la palabra 'garden' al principio?",
    "opciones": ["/dʒ/ sound", "/g/ sound", "/j/ sound", "/s/ sound"],
    "respuestaCorrecta": 1,
    "explicacion": "La tabla de pronunciación clasifica 'garden' bajo el sonido /g/ porque va antes de la letra 'a'."
  },
  {
    "id": 11,
    "pregunta": "¿Qué animal tiene 'the most amazing stripes'?",
    "opciones": ["The cheetah", "The giraffe", "The zebra", "The hyena"],
    "respuestaCorrecta": 2,
    "explicacion": "La lección 6 confirma que la cebra consiguió las rayas más increíbles."
  },
  {
    "id": 12,
    "pregunta": "¿Qué hace Zebra cuando se enfada con Baboon?",
    "opciones": ["He cries", "He goes away", "He sleeps", "He stamps his foot and makes a noise"],
    "respuestaCorrecta": 3,
    "explicacion": "En la viñeta 5 de la historia, Zebra patea el suelo y hace ruido al enfadarse."
  },
  {
    "id": 13,
    "pregunta": "¿Cuál es la forma correcta de decir 'el mejor' en inglés?",
    "opciones": ["the best", "the goodest", "the better", "the most good"],
    "respuestaCorrecta": 0,
    "explicacion": "El adjetivo 'good' es irregular y su forma superlativa es 'the best'."
  },
  {
    "id": 14,
    "pregunta": "¿Qué adjetivo significa tener miedo en inglés?",
    "opciones": ["Amazing", "Frightened", "Aggressive", "Important"],
    "respuestaCorrecta": 1,
    "explicacion": "En la historia de la cebra, los animales usan 'frightened' para expresar que tienen miedo de Baboon."
  },
  {
    "id": 15,
    "pregunta": "¿Qué animal es 'the most colourful' en el dibujo de la página 54?",
    "opciones": ["The lion", "The zebra", "The butterfly", "The meerkat"],
    "respuestaCorrecta": 2,
    "explicacion": "En el ejercicio de 'Ask and answer', se identifica a la mariposa como el animal más colorido."
  },
  {
    "id": 16,
    "pregunta": "¿Qué sonido tiene la palabra 'gym'?",
    "opciones": ["/g/ sound", "/s/ sound", "/i/ sound", "/dʒ/ sound"],
    "respuestaCorrecta": 3,
    "explicacion": "Según la regla fonética de la lección 3, 'gym' lleva el sonido /dʒ/ porque empieza por 'g' seguida de 'y'."
  },
  {
    "id": 17,
    "pregunta": "¿Qué adjetivo describe a alguien que no quiere compartir y solo piensa en sí mismo?",
    "opciones": ["Selfish", "Friendly", "Amazing", "Difficult"],
    "respuestaCorrecta": 0,
    "explicacion": "En la lección 5, se usa 'selfish' para describir la actitud de Baboon con el estanque."
  },
  {
    "id": 18,
    "pregunta": "Completa la frase gramatical: 'Zebra is the _____ aggressive animal of all'.",
    "opciones": ["more", "most", "best", "worst"],
    "respuestaCorrecta": 1,
    "explicacion": "Para adjetivos largos como 'aggressive', el superlativo se forma con 'the most'."
  },
  {
    "id": 19,
    "pregunta": "¿En qué países podrías vivir para ver koalas o elefantes según el repaso?",
    "opciones": ["Spain or France", "USA or Canada", "Sri Lanka or Australia", "Egypt or Morocco"],
    "respuestaCorrecta": 2,
    "explicacion": "La lección 8 pregunta al alumno si le gustaría vivir en Sri Lanka o Australia, países vinculados a estos animales."
  },
  {
    "id": 20,
    "pregunta": "En la canción, ¿qué se dice sobre todos los animales del mundo?",
    "opciones": ["Some are bad", "They are all big", "They are all scary", "Every animal has a place on this Earth"],
    "respuestaCorrecta": 3,
    "explicacion": "La canción de la lección 3 enseña que cada animal, grande o pequeño, tiene su lugar en la Tierra."
  },
  {
    "id": 21,
    "pregunta": "¿Qué animal de la canción es 'scarier than a baboon'?",
    "opciones": ["A lion", "A meerkat", "A giraffe", "A goat"],
    "respuestaCorrecta": 0,
    "explicacion": "La letra indica: 'A lion is more dangerous than a...', y asocia la peligrosidad/miedo con los grandes depredadores."
  },
  {
    "id": 22,
    "pregunta": "Si un adjetivo termina en 'y' como 'friendly', ¿cómo se forma su superlativo?",
    "opciones": ["most friendly", "unfriendliest", "friendlyest", "more friendly"],
    "respuestaCorrecta": 1,
    "explicacion": "La tabla gramatical muestra 'unfriendliest' como ejemplo de transformación de la 'y' en 'i' más '-est'."
  },
  {
    "id": 23,
    "pregunta": "¿Qué animal se menciona que puede trepar a los árboles ('climb a tree')?",
    "opciones": ["Elephant", "Crocodile", "Leopard", "Hippo"],
    "respuestaCorrecta": 2,
    "explicacion": "En la lección 8, se pide identificar animales que trepan árboles; el leopardo es el ejemplo típico en estos contextos."
  },
  {
    "id": 24,
    "pregunta": "¿Qué significa 'stripy'?",
    "opciones": ["Con manchas", "Con flores", "Liso", "Con rayas"],
    "respuestaCorrecta": 3,
    "explicacion": "El vocabulario de la lección 6 utiliza 'stripy' para describir las rayas de las cebras."
  },
  {
    "id": 25,
    "pregunta": "¿Qué sonido tiene la palabra 'guitar'?",
    "opciones": ["/g/ sound", "/dʒ/ sound", "/j/ sound", "/h/ sound"],
    "respuestaCorrecta": 0,
    "explicacion": "Se clasifica como sonido /g/ porque la 'g' no va seguida de e, i o y."
  },
  {
    "id": 26,
    "pregunta": "En la historia, ¿qué piensa Baboon sobre el estanque ('the pond')?",
    "opciones": ["He thinks it's for everyone", "He thinks that the pond is his", "He thinks the pond is dirty", "He thinks the pond is small"],
    "respuestaCorrecta": 1,
    "explicacion": "La viñeta 2 dice: 'He thinks that the pond is his', mostrando su actitud egoísta."
  },
  {
    "id": 27,
    "pregunta": "¿Qué animal de estos es 'the unfriendliest' en la gramática de la página 54?",
    "opciones": ["Giraffe", "Zebra", "Baboon", "Meerkat"],
    "respuestaCorrecta": 2,
    "explicacion": "La tabla de gramática utiliza a Baboon como ejemplo del animal más antipático (unfriendliest)."
  },
  {
    "id": 28,
    "pregunta": "¿Qué adjetivo describe algo que tiene manchas como un leopardo?",
    "opciones": ["Stripy", "Colourful", "Amazing", "Spotty"],
    "respuestaCorrecta": 3,
    "explicacion": "El vocabulario de la lección 6 incluye 'spotty' para referirse a animales con manchas (moteados)."
  },
  {
    "id": 29,
    "pregunta": "Completa la frase de la historia: 'Go away! I’m the most _____ animal here!'.",
    "opciones": ["important", "frightened", "difficult", "unfriendly"],
    "respuestaCorrecta": 0,
    "explicacion": "Baboon se autodenomina el animal más importante en la viñeta 2."
  },
  {
    "id": 30,
    "pregunta": "¿Qué animal suele estar a menudo en el agua según el repaso?",
    "opciones": ["Cheetah", "Crocodile", "Giraffe", "Lion"],
    "respuestaCorrecta": 1,
    "explicacion": "El cocodrilo es el animal acuático por excelencia mencionado en la lección 1 y el repaso."
  },
  {
    "id": 31,
    "pregunta": "¿Qué sonido tiene la palabra 'flamingo'?",
    "opciones": ["/dʒ/ sound", "/f/ sound", "/g/ sound", "/j/ sound"],
    "respuestaCorrecta": 2,
    "explicacion": "La palabra 'flamingo' empieza por /f/ pero en la lección se estudia su 'g' interna como sonido /g/."
  },
  {
    "id": 32,
    "pregunta": "¿Cuál es el antónimo (opuesto) de 'friendly' según el vocabulario?",
    "opciones": ["Important", "Amazing", "Difficult", "Unfriendly"],
    "respuestaCorrecta": 3,
    "explicacion": "La unidad presenta 'unfriendly' (antipático) como el opuesto de 'friendly'."
  },
  {
    "id": 33,
    "pregunta": "¿Qué animal es 'larger than a zebra' en la canción?",
    "opciones": ["An elephant", "A meerkat", "A hyena", "A baboon"],
    "respuestaCorrecta": 0,
    "explicacion": "La canción afirma: 'An elephant is larger than a zebra'."
  },
  {
    "id": 34,
    "pregunta": "¿Qué le pasó a Baboon al final de la historia?",
    "opciones": ["He stayed in the water", "He flies up high", "He makes a fire", "He gets stripes"],
    "respuestaCorrecta": 1,
    "explicacion": "La viñeta 6 dice que Baboon vuela alto tras el enfrentamiento con Zebra."
  },
  {
    "id": 35,
    "pregunta": "¿Cómo se dice 'el más asustado' en inglés?",
    "opciones": ["the frightenedest", "the more frightened", "the most frightened", "the best frightened"],
    "respuestaCorrecta": 2,
    "explicacion": "Al ser un adjetivo largo, 'frightened' forma el superlativo con 'the most'."
  },
  {
    "id": 36,
    "pregunta": "¿Qué animal aparece en la foto de la lección 7 sobre parques de vida salvaje?",
    "opciones": ["A koala", "A tiger", "A polar bear", "A red panda"],
    "respuestaCorrecta": 3,
    "explicacion": "La imagen de la lección 7 muestra a un panda rojo (red panda)."
  },
  {
    "id": 37,
    "pregunta": "En la fonética, ¿qué palabra rima con 'goat'?",
    "opciones": ["boat", "giraffe", "orange", "gym"],
    "respuestaCorrecta": 0,
    "explicacion": "El poema de la página 50 hace rimar 'goat' con 'boat' y 'coat'."
  },
  {
    "id": 38,
    "pregunta": "¿Qué adjetivo describe algo que es 'increíble'?",
    "opciones": ["Aggressive", "Amazing", "Difficult", "Important"],
    "respuestaCorrecta": 1,
    "explicacion": "El vocabulario de la lección 5 incluye 'amazing' para describir cosas asombrosas."
  },
  {
    "id": 39,
    "pregunta": "Completa con el superlativo: 'Giraffe is the most _____ animal at the pond'.",
    "opciones": ["aggressive", "stripy", "nervous", "selfish"],
    "respuestaCorrecta": 2,
    "explicacion": "En la página 54 se menciona que la jirafa es el animal más nervioso en el estanque."
  },
  {
    "id": 40,
    "pregunta": "¿Qué sonido tiene la palabra 'orange'?",
    "opciones": ["/g/ sound", "/o/ sound", "/r/ sound", "/dʒ/ sound"],
    "respuestaCorrecta": 3,
    "explicacion": "La 'g' en 'orange' suena /dʒ/ porque está antes de la letra 'e'."
  },
  {
    "id": 41,
    "pregunta": "¿Qué hace Zebra para detener a Baboon?",
    "opciones": ["He runs at Baboon", "He gives him a snack", "He calls a lion", "He goes to sleep"],
    "respuestaCorrecta": 0,
    "explicacion": "La viñeta 6 dice: 'Zebra runs at Baboon' para enfrentarse a él."
  },
  {
    "id": 42,
    "pregunta": "¿Cómo se pregunta '¿Cuál es el animal más peligroso?'?",
    "opciones": ["Which is the more dangerous animal?", "What is the most dangerous animal?", "What animal is dangerouser?", "Who is the dangerous animal?"],
    "respuestaCorrecta": 1,
    "explicacion": "Las preguntas sobre superlativos usan 'What is the most...' para adjetivos largos."
  },
  {
    "id": 43,
    "pregunta": "¿Qué animal es 'faster than a lion'?",
    "opciones": ["A crocodile", "A hyena", "A cheetah", "A meerkat"],
    "respuestaCorrecta": 2,
    "explicacion": "La canción de la unidad afirma que el guepardo (cheetah) es más rápido que el león."
  },
  {
    "id": 44,
    "pregunta": "¿Cuál es un adjetivo de personalidad mencionado en la unidad?",
    "opciones": ["Tall", "Blue", "Large", "Aggressive"],
    "respuestaCorrecta": 3,
    "explicacion": "A diferencia de los físicos, 'aggressive' describe el comportamiento o personalidad de Zebra en la historia."
  },
  {
    "id": 45,
    "pregunta": "¿Qué objeto usa Baboon en la historia que causa problemas?",
    "opciones": ["A fire", "A book", "A hat", "A ball"],
    "respuestaCorrecta": 0,
    "explicacion": "En la viñeta 4, Baboon está junto a un fuego (fire) impidiendo que otros beban."
  },
  {
    "id": 46,
    "pregunta": "¿Qué animal es 'more dangerous' que una hiena en la canción?",
    "opciones": ["A meerkat", "A lion", "A flamingo", "A zebra"],
    "respuestaCorrecta": 1,
    "explicacion": "La canción indica: 'A lion is more dangerous than a hyena'."
  },
  {
    "id": 47,
    "pregunta": "¿Cómo se siente Zebra en la viñeta 6?",
    "opciones": ["Frightened", "Happy", "Angry", "Thirsty"],
    "respuestaCorrecta": 2,
    "explicacion": "El texto dice: 'When Zebra is angry he’s also aggressive'."
  },
  {
    "id": 48,
    "pregunta": "¿Qué sonido tiene la palabra 'giraffe'?",
    "opciones": ["/g/ sound", "/j/ sound", "/s/ sound", "/dʒ/ sound"],
    "respuestaCorrecta": 3,
    "explicacion": "La 'g' de 'giraffe' suena /dʒ/ porque va antes de la letra 'i'."
  },
  {
    "id": 49,
    "pregunta": "¿Cuál es la forma correcta del superlativo para 'important'?",
    "opciones": ["the most important", "the importantest", "the more important", "the best important"],
    "respuestaCorrecta": 0,
    "explicacion": "Al ser un adjetivo de tres sílabas, requiere 'the most' para el superlativo."
  },
  {
    "id": 50,
    "pregunta": "¿Qué significa 'frightened'?",
    "opciones": ["Valiente", "Asustado", "Enfadado", "Cansado"],
    "respuestaCorrecta": 1,
    "explicacion": "Es el vocabulario clave de la unidad para expresar miedo, como siente la jirafa por el babuino."
  }
]
